{
	"animations": [
		{
			"offsets": [
				0,
				0
			],
			"loop": false,
			"fps": 24,
			"anim": "idle",
			"indices": [],
			"name": "Scratch Idle"
		},
		{
			"offsets": [
				0,
				0
			],
			"loop": false,
			"fps": 24,
			"anim": "singLEFT",
			"indices": [],
			"name": "Scratch Left"
		},
		{
			"loop": false,
			"offsets": [
				0,
				0
			],
			"anim": "singUPmiss",
			"fps": 24,
			"name": "Scratch Miss Up",
			"indices": []
		},
		{
			"loop": false,
			"offsets": [
				0,
				0
			],
			"anim": "singLEFTmiss",
			"fps": 24,
			"name": "Scratch Miss Left",
			"indices": []
		},
		{
			"loop": false,
			"offsets": [
				0,
				0
			],
			"anim": "singDOWNmiss",
			"fps": 24,
			"name": "Scratch Miss Down",
			"indices": []
		},
		{
			"loop": false,
			"offsets": [
				0,
				0
			],
			"anim": "singRIGHTmiss",
			"fps": 24,
			"name": "Scratch Miss Right",
			"indices": []
		},
		{
			"loop": false,
			"offsets": [
				0,
				0
			],
			"anim": "singUP",
			"fps": 24,
			"name": "Scratch Up",
			"indices": []
		},
		{
			"loop": false,
			"offsets": [
				0,
				0
			],
			"anim": "singRIGHT",
			"fps": 24,
			"name": "Scratch Right",
			"indices": []
		},
		{
			"loop": false,
			"offsets": [
				0,
				0
			],
			"anim": "singDOWN",
			"fps": 24,
			"name": "Scratch Down",
			"indices": []
		}
	],
	"no_antialiasing": false,
	"image": "characters/Scratch",
	"position": [
		0,
		350
	],
	"healthicon": "Scratch",
	"flip_x": false,
	"healthbar_colors": [
		161,
		161,
		161
	],
	"camera_position": [
		50,
		-60
	],
	"sing_duration": 4,
	"scale": 1
}